redi/TODO.md
redi/__init__.py
redi/batch.py
redi/form.py
redi/redi.py
redi/report.py
redi/upload.py
redi/utils/GetEmrData.py
redi/utils/SimpleConfigParser.py
redi/utils/__init__.py
redi/utils/component_id_to_loinc_code.xsd
redi/utils/csv2xml.py
redi/utils/date.month-abbreviation.template.xsl
redi/utils/date.year.template.xsl
redi/utils/formEvents.xsd
redi/utils/rawxml.py
redi/utils/redcapClient.py
redi/utils/redcap_records.py
redi/utils/redi_email.py
redi/utils/report.xsl
redi/utils/throttle.py
redi/utils/url_generator.py
redi-0.15.5.dist-info/AUTHORS.md
redi-0.15.5.dist-info/LICENSE.txt
redi-0.15.5.dist-info/METADATA
redi-0.15.5.dist-info/WHEEL
redi-0.15.5.dist-info/entry_points.txt
redi-0.15.5.dist-info/top_level.txt
redi-0.15.5.dist-info/RECORD
