Metadata-Version: 2.1
Name: redi
Version: 0.15.5
Summary: REDCap Electronic Data Importer
Home-page: https://github.com/ctsit/redi
Author: CTS-IT at the University of Florida
Author-email: ctsit@ctsi.ufl.edu
License: BSD 3-Clause
Download-URL: https://github.com/ctsit/redi/releases/tag/0.15.5
Keywords: EMR,EHR,REDCap,Clinical Data
Platform: UNKNOWN
Requires-Dist: requests (>=2.5.1)
Requires-Dist: lxml (>=3.3.5)
Requires-Dist: PyCap (>=1.0)
Requires-Dist: pysftp (>=0.2.8)
Requires-Dist: docopt (>=0.6.2)
Requires-Dist: pycrypto (>=2.6.1)
Requires-Dist: redcap-cli (>=0.1.0)
Requires-Dist: setuptools-scm (>=1.10.1)
